{
  "$schema": "https://developer.microsoft.com/json-schemas/fabric/item/report/definition/visualContainer/2.1.0/schema.json",
  "name": "e8833fa3125181f76e92",
  "position": {
    "x": 12.349955610646745,
    "y": 161.92164022847956,
    "z": 3000,
    "height": 67.238647213521162,
    "width": 190.73820331998863,
    "tabOrder": 5000
  },
  "visual": {
    "visualType": "slicer",
    "query": {
      "queryState": {
        "Values": {
          "projections": [
            {
              "field": {
                "Column": {
                  "Expression": {
                    "SourceRef": {
                      "Entity": "DimDepartment"
                    }
                  },
                  "Property": "Department_Name"
                }
              },
              "queryRef": "DimDepartment.Department_Name",
              "nativeQueryRef": "Department_Name",
              "active": true
            }
          ]
        }
      }
    },
    "objects": {
      "data": [
        {
          "properties": {
            "mode": {
              "expr": {
                "Literal": {
                  "Value": "'Dropdown'"
                }
              }
            }
          }
        }
      ],
      "general": [
        {
          "properties": {
            "orientation": {
              "expr": {
                "Literal": {
                  "Value": "1D"
                }
              }
            }
          }
        }
      ],
      "header": [
        {
          "properties": {
            "fontColor": {
              "solid": {
                "color": {
                  "expr": {
                    "ThemeDataColor": {
                      "ColorId": 0,
                      "Percent": 0
                    }
                  }
                }
              }
            }
          }
        }
      ]
    },
    "drillFilterOtherVisuals": true
  },
  "filterConfig": {
    "filters": [
      {
        "name": "41cfae9102d862051a04",
        "field": {
          "Column": {
            "Expression": {
              "SourceRef": {
                "Entity": "DimDepartment"
              }
            },
            "Property": "Department_Name"
          }
        },
        "type": "Categorical",
        "filter": {
          "Version": 2,
          "From": [
            {
              "Name": "d",
              "Entity": "DimDepartment",
              "Type": 0
            }
          ],
          "Where": [
            {
              "Condition": {
                "Not": {
                  "Expression": {
                    "In": {
                      "Expressions": [
                        {
                          "Column": {
                            "Expression": {
                              "SourceRef": {
                                "Source": "d"
                              }
                            },
                            "Property": "Department_Name"
                          }
                        }
                      ],
                      "Values": [
                        [
                          {
                            "Literal": {
                              "Value": "null"
                            }
                          }
                        ],
                        [
                          {
                            "Literal": {
                              "Value": "'Soft Skills'"
                            }
                          }
                        ]
                      ]
                    }
                  }
                }
              }
            }
          ]
        },
        "objects": {
          "general": [
            {
              "properties": {
                "isInvertedSelectionMode": {
                  "expr": {
                    "Literal": {
                      "Value": "true"
                    }
                  }
                }
              }
            }
          ]
        }
      }
    ]
  }
}