{
  "$schema": "https://developer.microsoft.com/json-schemas/fabric/item/report/definition/page/2.0.0/schema.json",
  "name": "ec2fa56850ccbc53a020",
  "displayName": "ENGAGEMENT VS PERFORMANCE",
  "displayOption": "FitToPage",
  "height": 720,
  "width": 1280,
  "objects": {
    "outspace": [
      {
        "properties": {
          "image": {
            "image": {
              "name": {
                "expr": {
                  "Literal": {
                    "Value": "'ITI Background.png'"
                  }
                }
              },
              "url": {
                "expr": {
                  "ResourcePackageItem": {
                    "PackageName": "RegisteredResources",
                    "PackageType": 1,
                    "ItemName": "ITI_Background07042564315770794.png"
                  }
                }
              },
              "scaling": {
                "expr": {
                  "Literal": {
                    "Value": "'Normal'"
                  }
                }
              }
            }
          }
        }
      }
    ],
    "background": [
      {
        "properties": {
          "image": {
            "image": {
              "name": {
                "expr": {
                  "Literal": {
                    "Value": "'ITI Background.png'"
                  }
                }
              },
              "url": {
                "expr": {
                  "ResourcePackageItem": {
                    "PackageName": "RegisteredResources",
                    "PackageType": 1,
                    "ItemName": "ITI_Background7559800890596335.png"
                  }
                }
              },
              "scaling": {
                "expr": {
                  "Literal": {
                    "Value": "'Normal'"
                  }
                }
              }
            }
          }
        }
      }
    ]
  }
}