{
  "$schema": "https://developer.microsoft.com/json-schemas/fabric/item/report/definition/visualContainer/2.1.0/schema.json",
  "name": "916790692eb9c0eba4e1",
  "position": {
    "x": 517.7941685527893,
    "y": 385.27812541605647,
    "z": 11000,
    "height": 90.798029556650249,
    "width": 244.17307948342432,
    "tabOrder": 9000
  },
  "visual": {
    "visualType": "image",
    "objects": {
      "general": [
        {
          "properties": {
            "imageUrl": {
              "expr": {
                "ResourcePackageItem": {
                  "PackageName": "RegisteredResources",
                  "PackageType": 1,
                  "ItemName": "Screenshot_2025-11-06_162432_(18926604334034614.png"
                }
              }
            }
          }
        }
      ]
    },
    "drillFilterOtherVisuals": true
  },
  "howCreated": "InsertVisualButton"
}