{
  "$schema": "https://developer.microsoft.com/json-schemas/fabric/item/report/definition/visualContainer/2.1.0/schema.json",
  "name": "0efb17efb5f4111b203b",
  "position": {
    "x": 218.88888888888889,
    "y": 207.77777777777777,
    "z": 3000,
    "height": 245.55555555555554,
    "width": 494.44444444444446,
    "tabOrder": 5000
  },
  "visual": {
    "visualType": "lineChart",
    "query": {
      "queryState": {
        "Category": {
          "projections": [
            {
              "field": {
                "HierarchyLevel": {
                  "Expression": {
                    "Hierarchy": {
                      "Expression": {
                        "PropertyVariationSource": {
                          "Expression": {
                            "SourceRef": {
                              "Entity": "DimDate"
                            }
                          },
                          "Name": "Variation",
                          "Property": "FullDate"
                        }
                      },
                      "Hierarchy": "Date Hierarchy"
                    }
                  },
                  "Level": "Year"
                }
              },
              "queryRef": "DimDate.FullDate.Variation.Date Hierarchy.Year",
              "nativeQueryRef": "FullDate Year",
              "active": true
            },
            {
              "field": {
                "HierarchyLevel": {
                  "Expression": {
                    "Hierarchy": {
                      "Expression": {
                        "PropertyVariationSource": {
                          "Expression": {
                            "SourceRef": {
                              "Entity": "DimDate"
                            }
                          },
                          "Name": "Variation",
                          "Property": "FullDate"
                        }
                      },
                      "Hierarchy": "Date Hierarchy"
                    }
                  },
                  "Level": "Quarter"
                }
              },
              "queryRef": "DimDate.FullDate.Variation.Date Hierarchy.Quarter",
              "nativeQueryRef": "FullDate Quarter",
              "active": false
            },
            {
              "field": {
                "HierarchyLevel": {
                  "Expression": {
                    "Hierarchy": {
                      "Expression": {
                        "PropertyVariationSource": {
                          "Expression": {
                            "SourceRef": {
                              "Entity": "DimDate"
                            }
                          },
                          "Name": "Variation",
                          "Property": "FullDate"
                        }
                      },
                      "Hierarchy": "Date Hierarchy"
                    }
                  },
                  "Level": "Month"
                }
              },
              "queryRef": "DimDate.FullDate.Variation.Date Hierarchy.Month",
              "nativeQueryRef": "FullDate Month",
              "active": false
            },
            {
              "field": {
                "HierarchyLevel": {
                  "Expression": {
                    "Hierarchy": {
                      "Expression": {
                        "PropertyVariationSource": {
                          "Expression": {
                            "SourceRef": {
                              "Entity": "DimDate"
                            }
                          },
                          "Name": "Variation",
                          "Property": "FullDate"
                        }
                      },
                      "Hierarchy": "Date Hierarchy"
                    }
                  },
                  "Level": "Day"
                }
              },
              "queryRef": "DimDate.FullDate.Variation.Date Hierarchy.Day",
              "nativeQueryRef": "FullDate Day",
              "active": false
            }
          ]
        },
        "Y": {
          "projections": [
            {
              "field": {
                "Measure": {
                  "Expression": {
                    "SourceRef": {
                      "Entity": "_Ziad"
                    }
                  },
                  "Property": "Avg. Instructor Rating"
                }
              },
              "queryRef": "_Ziad.Avg. Instructor Rating",
              "nativeQueryRef": "Avg. Instructor Rating"
            }
          ]
        }
      }
    },
    "objects": {
      "categoryAxis": [
        {
          "properties": {
            "labelColor": {
              "solid": {
                "color": {
                  "expr": {
                    "ThemeDataColor": {
                      "ColorId": 0,
                      "Percent": 0
                    }
                  }
                }
              }
            },
            "showAxisTitle": {
              "expr": {
                "Literal": {
                  "Value": "false"
                }
              }
            }
          }
        }
      ],
      "valueAxis": [
        {
          "properties": {
            "labelColor": {
              "solid": {
                "color": {
                  "expr": {
                    "ThemeDataColor": {
                      "ColorId": 0,
                      "Percent": 0
                    }
                  }
                }
              }
            },
            "showAxisTitle": {
              "expr": {
                "Literal": {
                  "Value": "false"
                }
              }
            }
          }
        }
      ],
      "legend": [
        {
          "properties": {
            "labelColor": {
              "solid": {
                "color": {
                  "expr": {
                    "ThemeDataColor": {
                      "ColorId": 0,
                      "Percent": 0
                    }
                  }
                }
              }
            }
          }
        }
      ],
      "lineStyles": [
        {
          "properties": {
            "lineChartType": {
              "expr": {
                "Literal": {
                  "Value": "'smooth'"
                }
              }
            },
            "lineStyle": {
              "expr": {
                "Literal": {
                  "Value": "'dashed'"
                }
              }
            }
          }
        }
      ]
    },
    "visualContainerObjects": {
      "title": [
        {
          "properties": {
            "text": {
              "expr": {
                "Literal": {
                  "Value": "'Ratings by Time'"
                }
              }
            },
            "show": {
              "expr": {
                "Literal": {
                  "Value": "true"
                }
              }
            },
            "heading": {
              "expr": {
                "Literal": {
                  "Value": "'Heading3'"
                }
              }
            },
            "titleWrap": {
              "expr": {
                "Literal": {
                  "Value": "true"
                }
              }
            },
            "fontColor": {
              "solid": {
                "color": {
                  "expr": {
                    "ThemeDataColor": {
                      "ColorId": 0,
                      "Percent": 0
                    }
                  }
                }
              }
            },
            "alignment": {
              "expr": {
                "Literal": {
                  "Value": "'center'"
                }
              }
            },
            "fontSize": {
              "expr": {
                "Literal": {
                  "Value": "12D"
                }
              }
            },
            "bold": {
              "expr": {
                "Literal": {
                  "Value": "true"
                }
              }
            },
            "italic": {
              "expr": {
                "Literal": {
                  "Value": "false"
                }
              }
            },
            "fontFamily": {
              "expr": {
                "Literal": {
                  "Value": "'Segoe UI'"
                }
              }
            }
          }
        }
      ],
      "background": [
        {
          "properties": {
            "show": {
              "expr": {
                "Literal": {
                  "Value": "true"
                }
              }
            },
            "color": {
              "solid": {
                "color": {
                  "expr": {
                    "ThemeDataColor": {
                      "ColorId": 2,
                      "Percent": 0
                    }
                  }
                }
              }
            },
            "transparency": {
              "expr": {
                "Literal": {
                  "Value": "90D"
                }
              }
            }
          }
        }
      ],
      "border": [
        {
          "properties": {
            "show": {
              "expr": {
                "Literal": {
                  "Value": "true"
                }
              }
            },
            "color": {
              "solid": {
                "color": {
                  "expr": {
                    "Literal": {
                      "Value": "'#2E3757'"
                    }
                  }
                }
              }
            },
            "radius": {
              "expr": {
                "Literal": {
                  "Value": "25D"
                }
              }
            },
            "width": {
              "expr": {
                "Literal": {
                  "Value": "8D"
                }
              }
            }
          }
        }
      ],
      "dropShadow": [
        {
          "properties": {
            "show": {
              "expr": {
                "Literal": {
                  "Value": "true"
                }
              }
            },
            "color": {
              "solid": {
                "color": {
                  "expr": {
                    "ThemeDataColor": {
                      "ColorId": 2,
                      "Percent": 0
                    }
                  }
                }
              }
            }
          }
        }
      ]
    },
    "drillFilterOtherVisuals": true
  }
}